cliffordopt/.DS_Store
cliffordopt/CliffordOps.py
cliffordopt/NHow.py
cliffordopt/__init__.py
cliffordopt/clifford_synthesis.py
cliffordopt/common.py
cliffordopt/opt/.DS_Store
cliffordopt/opt/GLD_2.db
cliffordopt/opt/GLD_3.db
cliffordopt/opt/GLD_4.db
cliffordopt/opt/GLD_5.db
cliffordopt/opt/GLD_6.db
cliffordopt/opt/GL_2.db
cliffordopt/opt/GL_3.db
cliffordopt/opt/GL_4.db
cliffordopt/opt/GL_5.db
cliffordopt/opt/GL_6.db
cliffordopt/opt/SpD_2.db
cliffordopt/opt/SpD_3.db
cliffordopt/opt/SpD_4.db
cliffordopt/opt/SpD_5.db
cliffordopt/opt/Sp_2.db
cliffordopt/opt/Sp_3.db
cliffordopt/opt/Sp_4.db
cliffordopt/opt/Sp_5.db
cliffordopt/requirements.txt
cliffordopt-1.0.4.dist-info/LICENCE
cliffordopt-1.0.4.dist-info/METADATA
cliffordopt-1.0.4.dist-info/WHEEL
cliffordopt-1.0.4.dist-info/RECORD
