Metadata-Version: 2.3
Name: cliffordopt
Version: 1.0.4
Summary: Clifford and CNOT Circuit optimisation.
License: GNUv3
Keywords: quantum computing,Clifford circuits,CNOT circuits,linear reversible circuits
Author: Mark Webster
Author-email: mark.acacia@gmail.com
Requires-Python: >=3.10,<4.0
Classifier: Development Status :: 3 - Alpha
Classifier: Intended Audience :: Science/Research
Classifier: License :: Other/Proprietary License
Classifier: Natural Language :: English
Classifier: Programming Language :: Python :: 3
Classifier: Programming Language :: Python :: 3.10
Classifier: Programming Language :: Python :: 3.11
Classifier: Programming Language :: Python :: 3.12
Classifier: Programming Language :: Python :: 3.13
Classifier: Topic :: Scientific/Engineering :: Mathematics
Classifier: Topic :: Scientific/Engineering :: Physics
Provides-Extra: dev
Requires-Dist: checks-superstaq (>=0.5.31) ; extra == "dev"
Requires-Dist: igraph (>=0.11.8)
Requires-Dist: numba (>=0.59.1)
Requires-Dist: numpy (>=1.26.2)
Requires-Dist: pyzx (>=0.8.0)
Requires-Dist: qiskit (>=1.1.1)
Requires-Dist: stim (>=1.13.0)
Requires-Dist: treap (>=2.0.10)
Project-URL: Repository, https://github.com/m-webster/CliffordOpt
